notion_formulas.py
notion_formulas-1.1.0.dist-info/METADATA
notion_formulas-1.1.0.dist-info/WHEEL
notion_formulas-1.1.0.dist-info/licenses/LICENSE
notion_formulas-1.1.0.dist-info/RECORD
