Metadata-Version: 2.1
Name: notion-formulas
Version: 1.1.0
Summary: Compose complex notion formulas in Python.
Project-URL: Documentation, https://github.com/wtolson/notion-formulas#readme
Project-URL: Issues, https://github.com/wtolson/notion-formulas/issues
Project-URL: Source, https://github.com/wtolson/notion-formulas
Author-email: Trevor Olson <trevor@heytrevor.com>
License-Expression: MIT
License-File: LICENSE
Classifier: Development Status :: 4 - Beta
Classifier: Programming Language :: Python
Classifier: Programming Language :: Python :: 3.7
Classifier: Programming Language :: Python :: 3.8
Classifier: Programming Language :: Python :: 3.9
Classifier: Programming Language :: Python :: 3.10
Classifier: Programming Language :: Python :: 3.11
Classifier: Programming Language :: Python :: Implementation :: CPython
Classifier: Programming Language :: Python :: Implementation :: PyPy
Requires-Python: >=3.7
Requires-Dist: typing-extensions; python_version < '3.10'
